sentistrength/__init__.py
sentistrength-0.0.9.dist-info/LICENSE
sentistrength-0.0.9.dist-info/METADATA
sentistrength-0.0.9.dist-info/WHEEL
sentistrength-0.0.9.dist-info/top_level.txt
sentistrength-0.0.9.dist-info/RECORD
