Metadata-Version: 2.1
Name: sentistrength
Version: 0.0.9
Summary: Python 3 Wrapper for SentiStrength, reads a single or multiple input with options for binary class or scale output.
Home-page: https://github.com/zhunhung/pysentistrength
Author: Zhun Hung
Author-email: yongzhunhung@gmail.com
License: UNKNOWN
Platform: UNKNOWN
Classifier: Programming Language :: Python :: 3
Classifier: License :: OSI Approved :: MIT License
Classifier: Operating System :: OS Independent
